pyNextcloud/__init__.py
pyNextcloud/config.py
pyNextcloud/nextcloud.py
pyNextcloud-1.0.dist-info/LICENSE
pyNextcloud-1.0.dist-info/METADATA
pyNextcloud-1.0.dist-info/WHEEL
pyNextcloud-1.0.dist-info/top_level.txt
pyNextcloud-1.0.dist-info/RECORD
