Metadata-Version: 2.2
Name: pyNextcloud
Version: 1.0
Summary: A Python library for interacting with Nextcloud via WebDAV
Home-page: 
Author: Mahir Shah
Author-email: dev@mahirshah.dev
License: MIT
Keywords: nextcloud webdav file-management
Classifier: Development Status :: 5 - Production/Stable
Classifier: License :: OSI Approved :: MIT License
Classifier: Programming Language :: Python :: 3
Classifier: Operating System :: OS Independent
Requires-Python: >=3.6
License-File: LICENSE
Requires-Dist: requests
Dynamic: author
Dynamic: author-email
Dynamic: classifier
Dynamic: description
Dynamic: description-content-type
Dynamic: keywords
Dynamic: license
Dynamic: requires-dist
Dynamic: requires-python
Dynamic: summary
